connector/__init__.py
connector/_version.py
connector/cli.py
connector/googlecloud.py
connector/googledrive.py
connector/init_conda_env.py
connector/remote.py
connector/restricted.py
connector/utils.py
connector2-0.2.3.dist-info/LICENSE.md
connector2-0.2.3.dist-info/METADATA
connector2-0.2.3.dist-info/WHEEL
connector2-0.2.3.dist-info/entry_points.txt
connector2-0.2.3.dist-info/top_level.txt
connector2-0.2.3.dist-info/RECORD
