Metadata-Version: 2.1
Name: connector2
Version: 0.2.3
Summary: Provides the default template for creating Python Package.
Home-page: https://github.com/tjsinghlab/connector
Author: Singh Lab
Author-email: singhlab@nygenome.org
License: MIT license
Requires-Python: >=3.7
License-File: LICENSE.md
Requires-Dist: autopep8 >=2.0.4
Requires-Dist: versioneer >=0.29
Requires-Dist: loguru >=0.7.2
